[
    {
        "Id": 1,
        "Name": "Monica"
      },
      {
        "Id": 2,
        "Name": "Lucia"
      },
      {
        "Id": 3,
        "Name": "Maira"
      },
      {
        "Id": 4,
        "Name": "Aurora"
      },
      {
        "Id": 5,
        "Name": "Maria"
      },
      {
        "Id": 6,
        "Name": "Eulalia"
      },
      {
        "Id": 7,
        "Name": "Adri"
      },
      {
        "Id": 8,
        "Name": "Ana"
      },{
        "Id": 9,
        "Name": "Mabelle"
      },
      {
        "Id": 10,
        "Name": "Zilma"
      }
]